hashnode_py/__about__.py
hashnode_py/__init__.py
hashnode_py/client.py
hashnode_py/queries/__init__.py
hashnode_py/queries/follow_queries.py
hashnode_py/queries/mutations.py
hashnode_py/queries/post_queries.py
hashnode_py/queries/publication_queries.py
hashnode_py/queries/tag_queries.py
hashnode_py/queries/user_queries.py
hashnode_py/resources/__init__.py
hashnode_py/resources/comment.py
hashnode_py/resources/draft.py
hashnode_py/resources/follow.py
hashnode_py/resources/post.py
hashnode_py/resources/publication.py
hashnode_py/resources/scheduled_post.py
hashnode_py/resources/tag.py
hashnode_py/resources/user.py
hashnode_py/resources/webhook.py
tests/__init__.py
tests/test_hashnode_client.py
tests/test_mutations.py
hashnode_py-0.0.1.dist-info/LICENSE
hashnode_py-0.0.1.dist-info/METADATA
hashnode_py-0.0.1.dist-info/WHEEL
hashnode_py-0.0.1.dist-info/top_level.txt
hashnode_py-0.0.1.dist-info/RECORD
