Metadata-Version: 2.1
Name: hashnode_py
Version: 0.0.1
Summary: Hashnode_Py, The python client to interact with hashnode graphql api
Home-page: https://github.com/TalaatHasanin/hashnode_py
Author: Talaat Hasanin
Author-email: talaat049@gmail.com
License: MIT
Classifier: Programming Language :: Python :: 3
Classifier: License :: OSI Approved :: MIT License
Classifier: Operating System :: OS Independent
Requires: gql
Requires: requests
Requires-Python: >=3.11
License-File: LICENSE
